vnpy_icetcore/__init__.py
vnpy_icetcore/icetcore_datafeed.py
vnpy_icetcore/icetcore_gateway.py
vnpy_icetcore/sample/__init__.py
vnpy_icetcore/sample/run.py
vnpy_icetcore-1.0.12.dist-info/LICENSE
vnpy_icetcore-1.0.12.dist-info/METADATA
vnpy_icetcore-1.0.12.dist-info/WHEEL
vnpy_icetcore-1.0.12.dist-info/top_level.txt
vnpy_icetcore-1.0.12.dist-info/RECORD
