Metadata-Version: 2.1
Name: vnpy_icetcore
Version: 1.0.12
Summary: vnpy icetcore gateway
Home-page: https://www.multicharts.cn/
Author: zxlee
Author-email: zxlee@icetech.com.cn
Classifier: Programming Language :: Python :: 3
Classifier: Operating System :: OS Independent
License-File: LICENSE
Requires-Dist: icetcore >=6.6.18
